html5/__init__.py
simple_html5/__init__.py
simple_html5-1.0.dist-info/METADATA
simple_html5-1.0.dist-info/WHEEL
simple_html5-1.0.dist-info/top_level.txt
simple_html5-1.0.dist-info/RECORD
