Metadata-Version: 2.1
Name: simple-html5
Version: 1.0
Summary: HTML5
Home-page: UNKNOWN
Author: Allen Sun
Author-email: allen.haha@hotmail.com
License: UNKNOWN
Platform: UNKNOWN
Classifier: Development Status :: 5 - Production/Stable
Classifier: Programming Language :: Python :: 3
Classifier: License :: OSI Approved :: MIT License
Classifier: Operating System :: OS Independent
Requires-Python: >=3.6
